marathon/__init__.py
marathon/client.py
marathon/exceptions.py
marathon/util.py
marathon/models/__init__.py
marathon/models/app.py
marathon/models/base.py
marathon/models/constraint.py
marathon/models/container.py
marathon/models/deployment.py
marathon/models/endpoint.py
marathon/models/events.py
marathon/models/group.py
marathon/models/info.py
marathon/models/queue.py
marathon/models/task.py
marathon-0.12.0.dist-info/LICENSE
marathon-0.12.0.dist-info/METADATA
marathon-0.12.0.dist-info/WHEEL
marathon-0.12.0.dist-info/top_level.txt
marathon-0.12.0.dist-info/RECORD
