Metadata-Version: 2.1
Name: marathon
Version: 0.12.0
Summary: Marathon Client Library
Home-page: https://github.com/thefactory/marathon-python
Author: Mike Babineau
Author-email: michael.babineau@gmail.com
License: MIT
Platform: Posix; MacOS X; Windows
Classifier: Development Status :: 5 - Production/Stable
Classifier: Intended Audience :: Developers
Classifier: Intended Audience :: System Administrators
Classifier: License :: OSI Approved :: MIT License
Classifier: Operating System :: OS Independent
Classifier: Programming Language :: Python :: 3
Classifier: Programming Language :: Python :: 3.6
Classifier: Programming Language :: Python :: 3.7
Classifier: Programming Language :: Python
Classifier: Topic :: Software Development :: Libraries :: Python Modules
Requires-Dist: requests (>=2.4.0)
Requires-Dist: requests-toolbelt (>=0.4.0)
